{
  "STARTERS": [
    {
      "title": "FRIES",
      "price": 3.5,
      "ingredients": "patate con buccia**",
      "allergens": null,
      "thumb": "./img/menu/starters/fries.webp",
      "available_in": [
        "LOCALE",
        "FOODTRUCK"
      ]
    },
    {
      "title": "BACON CHEDDAR FRIES",
      "price": 6.5,
      "ingredients": "patate con buccia**, crema cheddar home made, bacon croccante",
      "allergens": {
        "Allergeni": "Glutine, Latte"
      },
      "thumb": "./img/menu/starters/baconcheesefries.webp",
      "available_in": [
        "LOCALE"      ]
    },
    {
      "title": "ALETTE CRUNCHY",
      "price": "da 2,70€",
      "ingredients": "Alette di pollo pastellate e fritte laccate con salsa thai",
      "allergens": {
        "Allergeni": "Glutine, Senape"
      },
      "thumb": "./img/menu/starters/alettecrunchy.webp",
      "available_in": [
        "LOCALE"
      ]
    }
  ],
  "CICCIO'S BURGER": [
    {
      "title": "CRISPY GOAT",
      "price": 9.9,
      "ingredients": "bun, burger di pollo pastellato e fritto*, cheddar, bacon, lattuga, salsa Ciccio's",
      "allergens": {
        "Allergeni Panino": "Glutine, Uova, Latte",
        "Allergeni Salsa": "Uova, Senape, Arachidi, Pesce"
      },
      "thumb": "./img/menu/ciccios/crispygoat.webp",
      "available_in": [
        "LOCALE",
        "FOODTRUCK"
      ]
    },
    {
      "title": "BRIE",
      "price": 9.9,
      "ingredients": "bun, burger di manzo 170g, songino, brie, cipolla caramellata, bacon, salsa Ciccio's",
      "allergens": {
        "Allergeni Panino": "Glutine, Uova, Latte",
        "Allergeni Salsa": "Uova, Senape, Arachidi, Pesce"
      },
      "thumb": "./img/menu/ciccios/brie.webp",
      "available_in": [
        "LOCALE",
        "FOODTRUCK"
      ]
    },
    {
      "title": "TALÈ",
      "price": 9.9,
      "ingredients": "bun, burger di manzo 170g, songino, taleggio, guanciale croccante, pere caramellate, nocciole, salsa Ciccio's",
      "allergens": {
        "Allergeni Panino": "Glutine, Uova, Frutta a guscio, Latte",
        "Allergeni Salsa": "Uova, Senape, Arachidi, Pesce"
      },
      "thumb": "./img/menu/ciccios/tale.webp",
      "available_in": [
        "LOCALE",
        "FOODTRUCK"
      ]
    },
    {
      "title": "EGG",
      "price": 9.9,
      "ingredients": "bun, burger di manzo 170g, songino, cheddar, uovo fritto, guanciale croccante, maionese al tartufo",
      "allergens": {
        "Allergeni Panino": "Glutine, Uova, Latte",
        "Allergeni Salsa": "Uova, Senape, Arachidi, Pesce"
      },
      "thumb": "./img/menu/ciccios/egg.webp",
      "available_in": [
        "LOCALE",
        "FOODTRUCK"
      ]
    },
    {
      "title": "TUMA",
      "price": 9.9,
      "ingredients": "bun, burger di manzo 170g, songino, cipolla caramellata, tuma caramellata al miele, cipolla croccante, salsa Ciccio's",
      "allergens": {
        "Allergeni Panino": "Glutine, Uova, Latte",
        "Allergeni Salsa": "Uova, Senape, Arachidi, Pesce"
      },
      "thumb": "./img/menu/ciccios/tuma.webp",
      "available_in": [
        "LOCALE",
        "FOODTRUCK"
      ]
    },
    {
      "title": "PANCETTA",
      "price": 9.9,
      "ingredients": "bun, burger di manzo 170g, songino, scamorza, pancetta dolce, cipolla caramellata, confettura di fichi, cipolla croccante, salsa Ciccio's",
      "allergens": {
        "Allergeni Panino": "Glutine, Uova, Latte, Senape, Anidride solforosa e solfiti",
        "Allergeni Salsa": "Uova, Senape, Arachidi, Pesce"
      },
      "thumb": "./img/menu/ciccios/pancetta.webp",
      "available_in": [
        "LOCALE",
        "FOODTRUCK"
      ]
    },
    {
      "title": "DOUBLE TRIPLE",
      "price": 11.9,
      "ingredients": "bun, doppio burger di manzo 170g, triplo cheddar, doppio bacon, salsa Ciccio's",
      "allergens": {
        "Allergeni Panino": "Glutine, Uova, Latte",
        "Allergeni Salsa": "Uova, Senape, Arachidi, Pesce"
      },
      "thumb": "./img/menu/ciccios/doubletriple.webp",
      "available_in": [
        "LOCALE",
        "FOODTRUCK"
      ]
    },
    {
      "title": "SUPER CRISPY",
      "price": 9.9,
      "ingredients": "bun, burger di pollo fritto con panatura super croccante*, lattuga, pomodoro, maionese",
      "allergens": {
        "Allergeni Panino": "Glutine, Uova, Latte",
        "Allergeni Salsa": "Uova, Senape, Arachidi, Pesce"
      },
      "thumb": "./img/menu/ciccios/supercrispy.webp",
      "available_in": [
        "LOCALE",
        "FOODTRUCK"
      ]
    },
    {
      "title": "CHICKEN CBT",
      "price": 9.9,
      "ingredients": "bun, sovracoscia di pollo alla piastra, scamorza, lattuga, pomodoro, salsa white Ciccio's",
      "allergens": {
        "Allergeni Panino": "Glutine, Uova, Latte",
        "Allergeni Salsa": "Uova, Senape, Arachidi, Pesce"
      },
      "thumb": "./img/menu/ciccios/chickencbt.webp",
      "available_in": [
        "LOCALE",
        "FOODTRUCK"
      ]
    },
    {
      "title": "GREEN",
      "price": 9.9,
      "ingredients": "bun, burger vegetale, lattuga, cheddar, cipolla caramellata, salsa Ciccio's",
      "allergens": {
        "Allergeni Panino": "Glutine, Uova, Latte",
        "Allergeni Salsa": "Uova, Senape, Arachidi, Pesce"
      },
      "thumb": "./img/menu/ciccios/green.webp",
      "available_in": [
        "LOCALE",
        "FOODTRUCK"
      ]
    },
    {
      "title": "OLD SCHOOL",
      "price": 9.9,
      "ingredients": "bun, burger di manzo 170g, doppio cheddar, cipolla caramellata, doppio bacon, salsa white Ciccio's, salsa bbq",
      "allergens": {
        "Allergeni Panino": "Glutine, Uova, Latte",
        "Allergeni Salsa": "Uova, Senape, Arachidi, Pesce"
      },
      "thumb": "./img/menu/ciccios/oldschool.webp",
      "available_in": [
        "LOCALE",
        "FOODTRUCK"
      ]
    },
    {
      "title": "PORCHETTA",
      "price": 9.9,
      "ingredients": "bun, burger di manzo 170g, scamorza, lattuga, cipolla caramellata, porchetta, rosti di patate, salsa white Ciccio's",
      "allergens": {
        "Allergeni Panino": "Glutine, Uova, Latte",
        "Allergeni Salsa": "Uova, Senape, Arachidi, Pesce"
      },
      "thumb": "./img/menu/ciccios/porchetta.webp",
      "available_in": [
        "LOCALE",
        "FOODTRUCK"
      ]
    },
    {
      "title": "PANINO DELL'ESTATE",
      "price": 9.9,
      "ingredients": "bun, roast beef, robiolina con pomodoro semi-dry, tzatziki, grana, songino",
      "allergens": {
        "Allergeni": "Glutine, Uova, Latte, Solfiti, Frutta a guscio, Pesce"
      },
      "thumb": "./img/menu/ciccios/paninoestate-nobg.png",
      "available_in": [
        "LOCALE",
        "FOODTRUCK"
      ]
    },
    {
      "title": "CALABRESE",
      "price": 9.9,
      "ingredients": "bun, burger di manzo 170g, pecorino al peperoncino, cipolla caramellata alla birra, nduja, giri saltati, gocce di peperoncino",
      "allergens": {
        "Allergeni": "Glutine, Uova, Latte"
      },
      "thumb": "./img/menu/ciccios/calabrese.webp",
      "available_in": [
        "LOCALE",
        "FOODTRUCK"
      ]
    }
  ],
  "CLASSIC BURGER": [
    {
      "title": "HAMBURGER",
      "price": 6.5,
      "ingredients": "bun, burger di manzo 170g, salsa Ciccio's",
      "allergens": {
        "Allergeni Panino": "Glutine, Uova, Latte",
        "Allergeni Salsa": "Uova, Senape, Arachidi, Pesce"
      },
      "thumb": "./img/menu/classic/hamburger.webp",
      "available_in": [
        "LOCALE",
        "FOODTRUCK"
      ]
    },
    {
      "title": "CHEESEBURGER",
      "price": 7.9,
      "ingredients": "bun, burger di manzo 170g, cheddar, salsa Ciccio's",
      "allergens": {
        "Allergeni Panino": "Glutine, Uova, Latte",
        "Allergeni Salsa": "Uova, Senape, Arachidi, Pesce"
      },
      "thumb": "./img/menu/classic/cheeseburger.webp",
      "available_in": [
        "LOCALE",
        "FOODTRUCK"
      ]
    },
    {
      "title": "BACON CHEESEBURGER",
      "price": 8.9,
      "ingredients": "bun, burger di manzo 170g, cheddar, bacon, salsa Ciccio's",
      "allergens": {
        "Allergeni Panino": "Glutine, Uova, Latte",
        "Allergeni Salsa": "Uova, Senape, Arachidi, Pesce"
      },
      "thumb": "./img/menu/classic/baconcheeseburger.webp",
      "available_in": [
        "LOCALE",
        "FOODTRUCK"
      ]
    },
    {
      "title": "AMERICAN BACONCHEESE",
      "price": 8.9,
      "ingredients": "bun, burger di manzo 170g, cheddar, bacon, pomodoro, lattuga, salsa Ciccio's",
      "allergens": {
        "Allergeni Panino": "Glutine, Uova, Latte",
        "Allergeni Salsa": "Uova, Senape, Arachidi, Pesce"
      },
      "thumb": "./img/menu/classic/americanbaconcheese.webp",
      "available_in": [
        "LOCALE",
        "FOODTRUCK"
      ]
    }
  ],
  "MENU": [
    {
      "title": "HAPPY CICCIO'S ",
      "price": 6.9,
      "ingredients": null,
      "allergens": null,
      "thumb": "./img/menu/classic/happc-1.png",
      "available_in": [
        "LOCALE",
        "FOODTRUCK"
      ]
    },
    {
      "title": "HAMBURGER MENU",
      "price": 9,
      "ingredients": null,
      "allergens": null,
      "thumb": "./img/menu/classic/hamburger.webp",
      "available_in": [
        "LOCALE",
        "FOODTRUCK"
      ]
    },
    {
      "title": "CHEESEBURGER MENU ",
      "price": 9.4,
      "ingredients": null,
      "allergens": null,
      "thumb": "./img/menu/classic/cheeseburger.webp",
      "available_in": [
        "LOCALE",
        "FOODTRUCK"
      ]
    },
    {
      "title": "BACON CHEESEBURGER MENU",
      "price": 11.4,
      "ingredients": null,
      "allergens": null,
      "thumb": "./img/menu/classic/baconcheeseburger.webp",
      "available_in": [
        "LOCALE",
        "FOODTRUCK"
      ]
    },
    {
      "title": "AMERICAN BACONCHEESE MENU",
      "price": 11.4,
      "ingredients": null,
      "allergens": null,
      "thumb": "./img/menu/classic/americanbaconcheese.webp",
      "available_in": [
        "LOCALE",
        "FOODTRUCK"
      ]
    },
    {
      "title": "BRIE MENU",
      "price": 12.4,
      "ingredients": null,
      "allergens": null,
      "thumb": "./img/menu/ciccios/brie.webp",
      "available_in": [
        "LOCALE",
        "FOODTRUCK"
      ]
    },
    {
      "title": "CHICKEN CBT MENU",
      "price": 12.4,
      "ingredients": null,
      "allergens": null,
      "thumb": "./img/menu/ciccios/chickencbt.webp",
      "available_in": [
        "LOCALE",
        "FOODTRUCK"
      ]
    },
    {
      "title": "CRISPY GOAT MENU",
      "price": 12.4,
      "ingredients": null,
      "allergens": null,
      "thumb": "./img/menu/ciccios/crispygoat.webp",
      "available_in": [
        "LOCALE",
        "FOODTRUCK"
      ]
    },
    {
      "title": "DOUBLE TRIPLE MENU",
      "price": 14.4,
      "ingredients": null,
      "allergens": null,
      "thumb": "./img/menu/ciccios/doubletriple.webp",
      "available_in": [
        "LOCALE",
        "FOODTRUCK"
      ]
    },
    {
      "title": "EGG MENU",
      "price": 12.4,
      "ingredients": null,
      "allergens": null,
      "thumb": "./img/menu/ciccios/egg.webp",
      "available_in": [
        "LOCALE",
        "FOODTRUCK"
      ]
    },
    {
      "title": "GREEN MENU",
      "price": 12.4,
      "ingredients": null,
      "allergens": null,
      "thumb": "./img/menu/ciccios/brie.webp",
      "available_in": [
        "LOCALE",
        "FOODTRUCK"
      ]
    },
    {
      "title": "OLD SCHOOL MENU",
      "price": 12.4,
      "ingredients": null,
      "allergens": null,
      "thumb": "./img/menu/ciccios/oldschool.webp",
      "available_in": [
        "LOCALE",
        "FOODTRUCK"
      ]
    },
    {
      "title": "PANCETTA MENU",
      "price": 12.4,
      "ingredients": null,
      "allergens": null,
      "thumb": "./img/menu/ciccios/pancetta.webp",
      "available_in": [
        "LOCALE",
        "FOODTRUCK"
      ]
    },
    {
      "title": "PORCHETTA MENU",
      "price": 12.4,
      "ingredients": null,
      "allergens": null,
      "thumb": "./img/menu/ciccios/porchetta.webp",
      "available_in": [
        "LOCALE",
        "FOODTRUCK"
      ]
    },
    {
      "title": "SUPER CRISPY MENU",
      "price": 12.4,
      "ingredients": null,
      "allergens": null,
      "thumb": "./img/menu/ciccios/supercrispy.webp",
      "available_in": [
        "LOCALE",
        "FOODTRUCK"
      ]
    },
    {
      "title": "TALE' MENU",
      "price": 12.4,
      "ingredients": null,
      "allergens": null,
      "thumb": "./img/menu/ciccios/tale.webp",
      "available_in": [
        "LOCALE",
        "FOODTRUCK"
      ]
    },
    {
      "title": "TUMA MENU",
      "price": 12.4,
      "ingredients": null,
      "allergens": null,
      "thumb": "./img/menu/ciccios/tuma.webp",
      "available_in": [
        "LOCALE",
        "FOODTRUCK"
      ]
    },
    {
      "title": "CALABRESE MENU",
      "price": 12.4,
      "ingredients": null,
      "allergens": null,
      "thumb": "./img/menu/ciccios/calabrese.webp",
      "available_in": [
        "LOCALE",
        "FOODTRUCK"
      ]
    }
  ],
  "BEVANDE": [
    {
      "title": "ACQUA NATURALE 50CL",
      "price": 1.5,
      "ingredients": null,
      "allergens": null,
      "thumb": "./img/menu/bibite/acquanaturale.webp",
      "available_in": [
        "LOCALE",
        "FOODTRUCK"
      ]
    },
    {
      "title": "ACQUA FRIZZANTE 50CL",
      "price": 1.5,
      "ingredients": null,
      "allergens": null,
      "thumb": "./img/menu/bibite/acquafrizzante.webp",
      "available_in": [
        "LOCALE",
        "FOODTRUCK"
      ]
    },
    {
      "title": "FUZE TEA PESCA 33CL",
      "price": 2.5,
      "ingredients": null,
      "allergens": null,
      "thumb": "./img/menu/bibite/tepesca.webp",
      "available_in": [
        "LOCALE",
        "FOODTRUCK"
      ]
    },
    {
      "title": "FUZE TEA LIMONE 33CL",
      "price": 2.5,
      "ingredients": null,
      "allergens": null,
      "thumb": "./img/menu/bibite/telimone.webp",
      "available_in": [
        "LOCALE",
        "FOODTRUCK"
      ]
    },
    {
      "title": "SPRITE 33CL",
      "price": 2.5,
      "ingredients": null,
      "allergens": null,
      "thumb": "./img/menu/bibite/sprite.webp",
      "available_in": [
        "LOCALE",
        "FOODTRUCK"
      ]
    },
    {
      "title": "FANTA 33CL",
      "price": 2.5,
      "ingredients": null,
      "allergens": null,
      "thumb": "./img/menu/bibite/fanta.webp",
      "available_in": [
        "LOCALE",
        "FOODTRUCK"
      ]
    },
    {
      "title": "COCA COLA 33CL",
      "price": 2.5,
      "ingredients": null,
      "allergens": null,
      "thumb": "./img/menu/bibite/cocanormale.webp",
      "available_in": [
        "LOCALE",
        "FOODTRUCK"
      ]
    },
    {
      "title": "COCA COLA ZERO 33CL",
      "price": 2.5,
      "ingredients": null,
      "allergens": null,
      "thumb": "./img/menu/bibite/cocazero.webp",
      "available_in": [
        "LOCALE",
        "FOODTRUCK"
      ]
    },
    {
      "title": "CHINOTTO SAN PELLEGRINO 20CL",
      "price": 2.5,
      "ingredients": null,
      "allergens": null,
      "thumb": "./img/menu/bibite/chinotto.webp",
      "available_in": [
        "LOCALE",
        "FOODTRUCK"
      ]
    },
    {
      "title": "HEINEKEN 33CL",
      "price": 3.9,
      "ingredients": null,
      "allergens": null,
      "thumb": "./img/menu/bibite/heineken.webp",
      "available_in": [
        "LOCALE",
        "FOODTRUCK"
      ]
    },
    {
      "title": "HIPPANA BIANCA 33CL",
      "price": 5,
      "ingredients": null,
      "allergens": null,
      "thumb": "./img/menu/bibite/hippanabianca.webp",
      "available_in": [
        "LOCALE",
        "FOODTRUCK"
      ]
    },
    {
      "title": "HIPPANA BIONDA 33CL",
      "price": 5,
      "ingredients": null,
      "allergens": null,
      "thumb": "./img/menu/bibite/hippanabionda.webp",
      "available_in": [
        "LOCALE",
        "FOODTRUCK"
      ]
    },
    {
      "title": "HIPPANA ROSSA 33CL",
      "price": 5,
      "ingredients": null,
      "allergens": null,
      "thumb": "./img/menu/bibite/hippanarossa.webp",
      "available_in": [
        "LOCALE",
        "FOODTRUCK"
      ]
    },
    {
      "title": "HIPPANA AMBRATA 33CL",
      "price": 5,
      "ingredients": null,
      "allergens": null,
      "thumb": "./img/menu/bibite/hippanaambrata.webp",
      "available_in": [
        "LOCALE",
        "FOODTRUCK"
      ]
    }
  ],
  "SALSE": [
    {
      "title": "MAIONESE CICCIO'S 25gr",
      "price": 0.4,
      "ingredients": null,
      "allergens": null,
      "thumb": "./img/menu/salse/maioneseciccios.webp",
      "available_in": [
        "LOCALE",
        "FOODTRUCK"
      ]
    },
    {
      "title": "SALSA CHEDDAR CALDA 170ML",
      "price": 2.5,
      "ingredients": "salsa cheddar calda da 170ml",
      "allergens": {
        "Allergeni": "Glutine, Latte"
      },
      "thumb": "./img/menu/salse/salsacheddar170.webp",
      "available_in": [
        "LOCALE"      ]
    },
    {
      "title": "THAI 60ML",
      "price": 1.2,
      "ingredients": "salsa thai 60ml",
      "allergens": {
        "Allergeni": "Senape, Uova, Arachidi, Pesce"
      },
      "thumb": "./img/menu/salse/thai.webp",
      "available_in": [
        "LOCALE"      ]
    },
    {
      "title": "HOT THAI 60ML",
      "price": 1.2,
      "ingredients": "salsa hot thai 60ml",
      "allergens": {
        "Allergeni": "Senape, Uova, Arachidi, Pesce"
      },
      "thumb": "./img/menu/salse/hotthai.webp",
      "available_in": [
        "LOCALE"      ]
    },
    {
      "title": "SALSA CICCIO'S 25gr",
      "price": 0.4,
      "ingredients": null,
      "allergens": null,
      "thumb": "./img/menu/salse/salsaciccios.webp",
      "available_in": [
        "LOCALE",
        "FOODTRUCK"
      ]
    },
    {
      "title": "BBQ CICCIO'S 25gr",
      "price": 0.4,
      "ingredients": null,
      "allergens": null,
      "thumb": "./img/menu/salse/bbqciccios.webp",
      "available_in": [
        "LOCALE",
        "FOODTRUCK"
      ]
    },
    {
      "title": "KETCHUP CICCIO'S 25gr",
      "price": 0.4,
      "ingredients": null,
      "allergens": null,
      "thumb": "./img/menu/salse/ketchupciccios.webp",
      "available_in": [
        "LOCALE",
        "FOODTRUCK"
      ]
    }
  ],
  "SWEETS": [
    {
      "title": "KISS",
      "price": 3.5,
      "ingredients": "bun, nutella, bacon",
      "allergens": {
        "Allergeni": "Glutine, Frutta a guscio, Soia, Uova, Latte"
      },
      "thumb": "./img/menu/dolci/kiss.webp",
      "available_in": [
        "LOCALE"
      ]
    },
    {
      "title": "TIRAMICICCIO'S",
      "price": 4.5,
      "ingredients": "tiramisù",
      "allergens": {
        "Allergeni": "Glutine, Latte, Uova"
      },
      "thumb": "./img/menu/dolci/tiramiciccios.webp",
      "available_in": [
        "LOCALE"
      ]
    },
    {
      "title": "BROOKIES",
      "price": 4.5,
      "ingredients": "brookies",
      "allergens": {
        "Allergeni": "Glutine, Latte, Uova"
      },
      "thumb": "./img/menu/dolci/brookies.webp",
      "available_in": [
        "LOCALE"
      ]
    }
  ]  
}